ruword_frequency/__init__.py
ruword_frequency/frequency.py
ruword_frequency/source_reader.py
ruword_frequency-0.0.1.dist-info/METADATA
ruword_frequency-0.0.1.dist-info/RECORD
ruword_frequency-0.0.1.dist-info/WHEEL
ruword_frequency-0.0.1.dist-info/top_level.txt
