Metadata-Version: 2.1
Name: ruword-frequency
Version: 0.0.1
Summary: Library returns word frequence (ipm) by almost all russian words 
Home-page: https://github.com/Somewater/ruword_frequency
Author: Pavel Naydenov
Author-email: naydenov.p.v@gmail.com
License: UNKNOWN
Platform: UNKNOWN
Classifier: Programming Language :: Python :: 3
Classifier: License :: OSI Approved :: MIT License
Classifier: Operating System :: OS Independent
Classifier: Natural Language :: Russian
Requires-Dist: marisa-trie
